{
  "required": true,
  "package": "com.infamous.dungeons_mobs.mixin",
  "compatibilityLevel": "JAVA_17",
  "minVersion": "0.8.4",
  "refmap": "dungeons_mobs.refmap.json",
  "mixins": [
    "com.dephoegon.dungeons_mobs.mixin.AbstractArrowEntityMixin",
    "com.dephoegon.dungeons_mobs.mixin.AbstractHorseEntityMixin",
    "com.dephoegon.dungeons_mobs.mixin.ArrowAccessor",
    "com.dephoegon.dungeons_mobs.mixin.BrainAccessor",
    "com.dephoegon.dungeons_mobs.mixin.CropsBlockMixin",
    "com.dephoegon.dungeons_mobs.mixin.GoalSelectorAccessor",
    "com.dephoegon.dungeons_mobs.mixin.MansionTemplateMixin",
    "com.dephoegon.dungeons_mobs.mixin.PiglinAccessor",
    "com.dephoegon.dungeons_mobs.mixin.PiglinEntityMixin",
    "com.dephoegon.dungeons_mobs.mixin.ProjectileEntityMixin",
    "com.dephoegon.dungeons_mobs.mixin.RaidMixin",
    "com.dephoegon.dungeons_mobs.mixin.SpiderEntityMixin",
    "com.dephoegon.dungeons_mobs.mixin.TridentEntityAccessor",
    "com.dephoegon.dungeons_mobs.mixin.TridentEntityMixin",
    "com.dephoegon.dungeons_mobs.mixin.WitherSkeletonEntityMixin",
    "com.dephoegon.dungeons_mobs.mixin.ZombifiedPiglinEntityMixin"
  ],
  "client": [
    "com.dephoegon.dungeons_mobs.mixin.DrownedModelMixin",
    "com.dephoegon.dungeons_mobs.mixin.PiglinModelMixin",
    "com.dephoegon.dungeons_mobs.mixin.SpiderModelMixin",
    "com.dephoegon.dungeons_mobs.mixin.TridentRendererMixin"
  ],
  "injectors": {
    "defaultRequire": 1
  }
}